{
  "clients": [
    {
      "name": "Carmi",
      "category": "Schoenen",
      "server": "dedicated",
      "eCommerceData": {
        "conversions": 1000,
        "averageSell": 190.67,
        "totalRevenue": 72294.34,
        "conversionRate": 2.5,
        "lastMonthData": {
          "conversions": 800,
          "averageSell": 200,
          "totalRevenue": 34300,
          "conversionRate": 4
        }
      },
      "analyticsData": {
        "totalSessions": 63746,
        "totalUsers": 63780,
        "pageviews": 606901,
        "averagePagesPerSessions": 9.56,
        "bouncerate": 20.8,
        "lastMonthData": {
          "totalSessions": 31746,
          "totalUsers": 21780,
          "pageviews": 406901
        },
        "aquisition": {
          "organic": 7010,
          "direct": 8985,
          "social": 1554,
          "referral": 1499,
          "paid": 542
        }
      }
    },
    {
      "name": "Bobo",
      "category": "Medisch",
      "server": "dedicated",
      "eCommerceData": {
        "conversions": 410,
        "averageSell": 200.29,
        "totalRevenue": 29714.18,
        "conversionRate": 2.5,
        "lastMonthData": {
          "conversions": 800,
          "averageSell": 200,
          "totalRevenue": 30000,
          "conversionRate": 4
        }
      },
      "analyticsData": {
        "totalSessions": 26960,
        "totalUsers": 25140,
        "pageviews": 23992,
        "averagePagesPerSessions": 9.96,
        "bouncerate": 23.62,
        "lastMonthData": {
          "totalSessions": 31746,
          "totalUsers": 21780,
          "pageviews": 406901
        },
        "aquisition": {
          "organic": 6179,
          "direct": 1456,
          "social": 2350,
          "referral": 355
        }
      }
    },
    {
      "name": "Schaeps",
      "category": "Fashion",
      "server": "dedicated",
      "eCommerceData": {
        "conversions": 500,
        "averageSell": 91.29,
        "totalRevenue": 3000.18,
        "conversionRate": 1.3,
        "lastMonthData": {
          "conversions": 800,
          "averageSell": 200,
          "totalRevenue": 5000,
          "conversionRate": 4
        }
      },
      "analyticsData": {
        "totalSessions": 13960,
        "totalUsers": 10140,
        "pageviews": 138992,
        "averagePagesPerSessions": 9.96,
        "bouncerate": 33.62,
        "lastMonthData": {
          "totalSessions": 31746,
          "totalUsers": 21780,
          "pageviews": 406901
        },
        "aquisition": {
          "organic": 3179,
          "direct": 1456,
          "social": 5350,
          "referral": 155
        }
      }
    },
    {
      "name": "Lieve vriendjes",
      "category": "Fashion",
      "server": "dedicated",
      "eCommerceData": {
        "conversions": 400,
        "averageSell": 91.29,
        "totalRevenue": 5000.18,
        "conversionRate": 1.8,
        "lastMonthData": {
          "conversions": 800,
          "averageSell": 200,
          "totalRevenue": 6000,
          "conversionRate": 4
        }
      },
      "analyticsData": {
        "totalSessions": 33960,
        "totalUsers": 10140,
        "pageviews": 138992,
        "averagePagesPerSessions": 9.96,
        "bouncerate": 33.62,
        "lastMonthData": {
          "totalSessions": 31746,
          "totalUsers": 21780,
          "pageviews": 406901
        },
        "aquisition": {
          "organic": 3179,
          "direct": 1456,
          "social": 5350,
          "referral": 155
        }
      }
    },
    {
      "name": "Delsport",
      "category": "Fashion",
      "server": "dedicated",
      "eCommerceData": {
        "conversions": 800,
        "averageSell": 91.29,
        "totalRevenue": 7000.18,
        "conversionRate": 0.6,
        "lastMonthData": {
          "conversions": 800,
          "averageSell": 200,
          "totalRevenue": 7500,
          "conversionRate": 4
        }
      },
      "analyticsData": {
        "totalSessions": 13960,
        "totalUsers": 10140,
        "pageviews": 138992,
        "averagePagesPerSessions": 9.96,
        "bouncerate": 33.62,
        "lastMonthData": {
          "totalSessions": 31746,
          "totalUsers": 21780,
          "pageviews": 406901
        },
        "aquisition": {
          "organic": 3179,
          "direct": 1456,
          "social": 5350,
          "referral": 155
        }
      }
    },
    {
      "name": "Fashion team",
      "category": "Fashion",
      "server": "dedicated",
      "eCommerceData": {
        "conversions": 450,
        "averageSell": 91.29,
        "totalRevenue": 4000.18,
        "conversionRate": 2.3,
        "lastMonthData": {
          "conversions": 800,
          "averageSell": 200,
          "totalRevenue": 2000,
          "conversionRate": 4
        }
      },
      "analyticsData": {
        "totalSessions": 13960,
        "totalUsers": 10140,
        "pageviews": 138992,
        "averagePagesPerSessions": 9.96,
        "bouncerate": 33.62,
        "lastMonthData": {
          "totalSessions": 31746,
          "totalUsers": 21780,
          "pageviews": 406901
        },
        "aquisition": {
          "organic": 3179,
          "direct": 1456,
          "social": 5350,
          "referral": 155
        }
      }
    },
    {
      "name": "Fonce",
      "category": "Medisch",
      "server": "dedicated",
      "eCommerceData": {
        "conversions": 410,
        "averageSell": 200.29,
        "totalRevenue": 2970.18,
        "conversionRate": 2.53,
        "lastMonthData": {
          "conversions": 800,
          "averageSell": 200,
          "totalRevenue": 9000,
          "conversionRate": 4
        }
      },
      "analyticsData": {
        "totalSessions": 26960,
        "totalUsers": 25140,
        "pageviews": 23992,
        "averagePagesPerSessions": 9.96,
        "bouncerate": 23.62,
        "lastMonthData": {
          "totalSessions": 31746,
          "totalUsers": 21780,
          "pageviews": 406901
        },
        "aquisition": {
          "organic": 6179,
          "direct": 1456,
          "social": 2350,
          "referral": 355
        }
      }
    },
    {
      "name": "De dappere stappers",
      "category": "Fashion",
      "server": "dedicated",
      "eCommerceData": {
        "conversions": 410,
        "averageSell": 200.29,
        "totalRevenue": 2970.18,
        "conversionRate": 2.55,
        "lastMonthData": {
          "conversions": 800,
          "averageSell": 200,
          "totalRevenue": 10000,
          "conversionRate": 4
        }
      },
      "analyticsData": {
        "totalSessions": 26960,
        "totalUsers": 25140,
        "pageviews": 23992,
        "averagePagesPerSessions": 9.96,
        "bouncerate": 23.62,
        "lastMonthData": {
          "totalSessions": 31746,
          "totalUsers": 21780,
          "pageviews": 406901
        },
        "aquisition": {
          "organic": 6179,
          "direct": 1456,
          "social": 2350,
          "referral": 355
        }
      }
    },
    {
      "name": "Carmi Zemst",
      "category": "Medisch",
      "server": "dedicated",
      "eCommerceData": {
        "conversions": 410,
        "averageSell": 200.29,
        "totalRevenue": 2970.18,
        "conversionRate": 2.5,
        "lastMonthData": {
          "conversions": 800,
          "averageSell": 200,
          "totalRevenue": 1000,
          "conversionRate": 4
        }
      },
      "analyticsData": {
        "totalSessions": 26960,
        "totalUsers": 25140,
        "pageviews": 23992,
        "averagePagesPerSessions": 9.96,
        "bouncerate": 23.62,
        "lastMonthData": {
          "totalSessions": 31746,
          "totalUsers": 21780,
          "pageviews": 406901
        },
        "aquisition": {
          "organic": 6179,
          "direct": 1456,
          "social": 2350,
          "referral": 355
        }
      }
    },
    {
      "name": "Carmi Zemst Mephisto",
      "category": "Fashion",
      "server": "dedicated",
      "eCommerceData": {
        "conversions": 400,
        "averageSell": 91.29,
        "totalRevenue": 2000.18,
        "conversionRate": 5.3,
        "lastMonthData": {
          "conversions": 800,
          "averageSell": 200,
          "totalRevenue": 1000,
          "conversionRate": 4
        }
      },
      "analyticsData": {
        "totalSessions": 13960,
        "totalUsers": 10140,
        "pageviews": 138992,
        "averagePagesPerSessions": 9.96,
        "bouncerate": 33.62,
        "lastMonthData": {
          "totalSessions": 31746,
          "totalUsers": 21780,
          "pageviews": 406901
        },
        "aquisition": {
          "organic": 3179,
          "direct": 1456,
          "social": 5350,
          "referral": 155
        }
      }
    },
    {
      "name": "Castard",
      "category": "Schoenen",
      "server": "dedicated",
      "eCommerceData": {
        "conversions": 410,
        "averageSell": 200.29,
        "totalRevenue": 2970.18,
        "conversionRate": 2.54,
        "lastMonthData": {
          "conversions": 800,
          "averageSell": 200,
          "totalRevenue": 1000,
          "conversionRate": 4
        }
      },
      "analyticsData": {
        "totalSessions": 26960,
        "totalUsers": 25140,
        "pageviews": 23992,
        "averagePagesPerSessions": 9.96,
        "bouncerate": 23.62,
        "lastMonthData": {
          "totalSessions": 31746,
          "totalUsers": 21780,
          "pageviews": 406901
        },
        "aquisition": {
          "organic": 6179,
          "direct": 1456,
          "social": 2350,
          "referral": 355
        }
      }
    },
    {
      "name": "Print a gift",
      "category": "Schoenen",
      "server": "dedicated",
      "eCommerceData": {
        "conversions": 410,
        "averageSell": 200.29,
        "totalRevenue": 2970.18,
        "conversionRate": 2.53,
        "lastMonthData": {
          "conversions": 800,
          "averageSell": 200,
          "totalRevenue": 5500,
          "conversionRate": 4
        }
      },
      "analyticsData": {
        "totalSessions": 26960,
        "totalUsers": 25140,
        "pageviews": 23992,
        "averagePagesPerSessions": 9.96,
        "bouncerate": 23.62,
        "lastMonthData": {
          "totalSessions": 31746,
          "totalUsers": 21780,
          "pageviews": 406901
        },
        "aquisition": {
          "organic": 6179,
          "direct": 1456,
          "social": 2350,
          "referral": 355
        }
      }
    },
    {
      "name": "Modemakers",
      "category": "Fashion",
      "server": "dedicated",
      "eCommerceData": {
        "conversions": 200,
        "averageSell": 91.29,
        "totalRevenue": 6060.18,
        "conversionRate": 2,
        "lastMonthData": {
          "conversions": 800,
          "averageSell": 200,
          "totalRevenue": 5000,
          "conversionRate": 4
        }
      },
      "analyticsData": {
        "totalSessions": 13960,
        "totalUsers": 10140,
        "pageviews": 138992,
        "averagePagesPerSessions": 9.96,
        "bouncerate": 33.62,
        "lastMonthData": {
          "totalSessions": 31746,
          "totalUsers": 21780,
          "pageviews": 406901
        },
        "aquisition": {
          "organic": 3179,
          "direct": 1456,
          "social": 5350,
          "referral": 155
        }
      }
    },
    {
      "name": "Miz Mooz",
      "category": "Schoenen",
      "server": "dedicated",
      "eCommerceData": {
        "conversions": 410,
        "averageSell": 200.29,
        "totalRevenue": 29700.18,
        "conversionRate": 2.5,
        "lastMonthData": {
          "conversions": 800,
          "averageSell": 200,
          "totalRevenue": 25000,
          "conversionRate": 4
        }
      },
      "analyticsData": {
        "totalSessions": 26960,
        "totalUsers": 25140,
        "pageviews": 23992,
        "averagePagesPerSessions": 9.96,
        "bouncerate": 23.62,
        "lastMonthData": {
          "totalSessions": 31746,
          "totalUsers": 21780,
          "pageviews": 406901
        },
        "aquisition": {
          "organic": 6179,
          "direct": 1456,
          "social": 2350,
          "referral": 355
        }
      }
    },
    {
      "name": "Pericles outlet",
      "category": "Fashion",
      "server": "dedicated",
      "eCommerceData": {
        "conversions": 410,
        "averageSell": 200.29,
        "totalRevenue": 2973.18,
        "conversionRate": 2.58,
        "lastMonthData": {
          "conversions": 800,
          "averageSell": 200,
          "totalRevenue": 1000,
          "conversionRate": 4
        }
      },
      "analyticsData": {
        "totalSessions": 26960,
        "totalUsers": 25140,
        "pageviews": 23992,
        "averagePagesPerSessions": 9.96,
        "bouncerate": 23.62,
        "lastMonthData": {
          "totalSessions": 31746,
          "totalUsers": 21780,
          "pageviews": 406901
        },
        "aquisition": {
          "organic": 6179,
          "direct": 1456,
          "social": 2350,
          "referral": 355
        }
      }
    },
    {
      "name": "Tweedehands laptops",
      "category": "Medisch",
      "server": "dedicated",
      "eCommerceData": {
        "conversions": 1100,
        "averageSell": 91.29,
        "totalRevenue": 15500.18,
        "conversionRate": 1.5,
        "lastMonthData": {
          "conversions": 800,
          "averageSell": 200,
          "totalRevenue": 20000,
          "conversionRate": 4
        }
      },
      "analyticsData": {
        "totalSessions": 13960,
        "totalUsers": 10140,
        "pageviews": 138992,
        "averagePagesPerSessions": 9.96,
        "bouncerate": 33.62,
        "lastMonthData": {
          "totalSessions": 31746,
          "totalUsers": 21780,
          "pageviews": 406901
        },
        "aquisition": {
          "organic": 3179,
          "direct": 1456,
          "social": 5350,
          "referral": 155
        }
      }
    },
    {
      "name": "MJJK",
      "category": "Medisch",
      "server": "dedicated",
      "eCommerceData": {
        "conversions": 410,
        "averageSell": 200.29,
        "totalRevenue": 29714.18,
        "conversionRate": 2.5,
        "lastMonthData": {
          "conversions": 800,
          "averageSell": 200,
          "totalRevenue": 30000,
          "conversionRate": 4
        }
      },
      "analyticsData": {
        "totalSessions": 26960,
        "totalUsers": 25140,
        "pageviews": 23992,
        "averagePagesPerSessions": 9.96,
        "bouncerate": 23.62,
        "lastMonthData": {
          "totalSessions": 31746,
          "totalUsers": 21780,
          "pageviews": 406901
        },
        "aquisition": {
          "organic": 6179,
          "direct": 1456,
          "social": 2350,
          "referral": 355
        }
      }
    },
    {
      "name": "Outr",
      "category": "Medisch",
      "server": "dedicated",
      "eCommerceData": {
        "conversions": 410,
        "averageSell": 200.29,
        "totalRevenue": 29714.18,
        "conversionRate": 2.5,
        "lastMonthData": {
          "conversions": 800,
          "averageSell": 200,
          "totalRevenue": 30000,
          "conversionRate": 4
        }
      },
      "analyticsData": {
        "totalSessions": 26960,
        "totalUsers": 25140,
        "pageviews": 23992,
        "averagePagesPerSessions": 9.96,
        "bouncerate": 23.62,
        "lastMonthData": {
          "totalSessions": 31746,
          "totalUsers": 21780,
          "pageviews": 406901
        },
        "aquisition": {
          "organic": 6179,
          "direct": 1456,
          "social": 2350,
          "referral": 355
        }
      }
    },
    {
      "name": "Bohero",
      "category": "Medisch",
      "server": "dedicated",
      "eCommerceData": {
        "conversions": 410,
        "averageSell": 200.29,
        "totalRevenue": 29714.18,
        "conversionRate": 2.5,
        "lastMonthData": {
          "conversions": 800,
          "averageSell": 200,
          "totalRevenue": 30000,
          "conversionRate": 4
        }
      },
      "analyticsData": {
        "totalSessions": 26960,
        "totalUsers": 25140,
        "pageviews": 23992,
        "averagePagesPerSessions": 9.96,
        "bouncerate": 23.62,
        "lastMonthData": {
          "totalSessions": 31746,
          "totalUsers": 21780,
          "pageviews": 406901
        },
        "aquisition": {
          "organic": 6179,
          "direct": 1456,
          "social": 2350,
          "referral": 355
        }
      }
    },
    {
      "name": "Mamado",
      "category": "Medisch",
      "server": "dedicated",
      "eCommerceData": {
        "conversions": 410,
        "averageSell": 200.29,
        "totalRevenue": 29714.18,
        "conversionRate": 2.5,
        "lastMonthData": {
          "conversions": 800,
          "averageSell": 200,
          "totalRevenue": 30000,
          "conversionRate": 4
        }
      },
      "analyticsData": {
        "totalSessions": 26960,
        "totalUsers": 25140,
        "pageviews": 23992,
        "averagePagesPerSessions": 9.96,
        "bouncerate": 23.62,
        "lastMonthData": {
          "totalSessions": 31746,
          "totalUsers": 21780,
          "pageviews": 406901
        },
        "aquisition": {
          "organic": 6179,
          "direct": 1456,
          "social": 2350,
          "referral": 355
        }
      }
    },
    {
      "name": "Alpha",
      "category": "Medisch",
      "server": "dedicated",
      "eCommerceData": {
        "conversions": 410,
        "averageSell": 200.29,
        "totalRevenue": 29714.18,
        "conversionRate": 2.5,
        "lastMonthData": {
          "conversions": 800,
          "averageSell": 200,
          "totalRevenue": 30000,
          "conversionRate": 4
        }
      },
      "analyticsData": {
        "totalSessions": 26960,
        "totalUsers": 25140,
        "pageviews": 23992,
        "averagePagesPerSessions": 9.96,
        "bouncerate": 23.62,
        "lastMonthData": {
          "totalSessions": 31746,
          "totalUsers": 21780,
          "pageviews": 406901
        },
        "aquisition": {
          "organic": 6179,
          "direct": 1456,
          "social": 2350,
          "referral": 355
        }
      }
    },
    {
      "name": "Mode information",
      "category": "Medisch",
      "server": "dedicated",
      "eCommerceData": {
        "conversions": 410,
        "averageSell": 200.29,
        "totalRevenue": 29714.18,
        "conversionRate": 2.5,
        "lastMonthData": {
          "conversions": 800,
          "averageSell": 200,
          "totalRevenue": 30000,
          "conversionRate": 4
        }
      },
      "analyticsData": {
        "totalSessions": 26960,
        "totalUsers": 25140,
        "pageviews": 23992,
        "averagePagesPerSessions": 9.96,
        "bouncerate": 23.62,
        "lastMonthData": {
          "totalSessions": 31746,
          "totalUsers": 21780,
          "pageviews": 406901
        },
        "aquisition": {
          "organic": 6179,
          "direct": 1456,
          "social": 2350,
          "referral": 355
        }
      }
    },
    {
      "name": "Schoenen De Proost",
      "category": "Medisch",
      "server": "dedicated",
      "eCommerceData": {
        "conversions": 410,
        "averageSell": 200.29,
        "totalRevenue": 29714.18,
        "conversionRate": 2.5,
        "lastMonthData": {
          "conversions": 800,
          "averageSell": 200,
          "totalRevenue": 30000,
          "conversionRate": 4
        }
      },
      "analyticsData": {
        "totalSessions": 26960,
        "totalUsers": 25140,
        "pageviews": 23992,
        "averagePagesPerSessions": 9.96,
        "bouncerate": 23.62,
        "lastMonthData": {
          "totalSessions": 31746,
          "totalUsers": 21780,
          "pageviews": 406901
        },
        "aquisition": {
          "organic": 6179,
          "direct": 1456,
          "social": 2350,
          "referral": 355
        }
      }
    },
    {
      "name": "Buffalini",
      "category": "Category 1",
      "server": "dedicated",
      "eCommerceData": {
        "conversions": 410,
        "averageSell": 200.29,
        "totalRevenue": 29714.18,
        "conversionRate": 2.5,
        "lastMonthData": {
          "conversions": 800,
          "averageSell": 200,
          "totalRevenue": 30000,
          "conversionRate": 4
        }
      },
      "analyticsData": {
        "totalSessions": 26960,
        "totalUsers": 25140,
        "pageviews": 23992,
        "averagePagesPerSessions": 9.96,
        "bouncerate": 23.62,
        "lastMonthData": {
          "totalSessions": 31746,
          "totalUsers": 21780,
          "pageviews": 406901
        },
        "aquisition": {
          "organic": 6179,
          "direct": 1456,
          "social": 2350,
          "referral": 355
        }
      }
    },
    {
      "name": "Eglantier Hifi",
      "category": "Category 2",
      "server": "dedicated",
      "eCommerceData": {
        "conversions": 410,
        "averageSell": 200.29,
        "totalRevenue": 29714.18,
        "conversionRate": 2.5,
        "lastMonthData": {
          "conversions": 800,
          "averageSell": 200,
          "totalRevenue": 30000,
          "conversionRate": 4
        }
      },
      "analyticsData": {
        "totalSessions": 26960,
        "totalUsers": 25140,
        "pageviews": 23992,
        "averagePagesPerSessions": 9.96,
        "bouncerate": 23.62,
        "lastMonthData": {
          "totalSessions": 31746,
          "totalUsers": 21780,
          "pageviews": 406901
        },
        "aquisition": {
          "organic": 6179,
          "direct": 1456,
          "social": 2350,
          "referral": 355
        }
      }
    },
    {
      "name": "Leirovins",
      "category": "Category 3",
      "server": "dedicated",
      "eCommerceData": {
        "conversions": 410,
        "averageSell": 200.29,
        "totalRevenue": 29714.18,
        "conversionRate": 2.5,
        "lastMonthData": {
          "conversions": 800,
          "averageSell": 200,
          "totalRevenue": 30000,
          "conversionRate": 4
        }
      },
      "analyticsData": {
        "totalSessions": 26960,
        "totalUsers": 25140,
        "pageviews": 23992,
        "averagePagesPerSessions": 9.96,
        "bouncerate": 23.62,
        "lastMonthData": {
          "totalSessions": 31746,
          "totalUsers": 21780,
          "pageviews": 406901
        },
        "aquisition": {
          "organic": 6179,
          "direct": 1456,
          "social": 2350,
          "referral": 355
        }
      }
    },
    {
      "name": "For Stars",
      "category": "Category 4",
      "server": "dedicated",
      "eCommerceData": {
        "conversions": 410,
        "averageSell": 200.29,
        "totalRevenue": 29714.18,
        "conversionRate": 2.5,
        "lastMonthData": {
          "conversions": 800,
          "averageSell": 200,
          "totalRevenue": 30000,
          "conversionRate": 4
        }
      },
      "analyticsData": {
        "totalSessions": 26960,
        "totalUsers": 25140,
        "pageviews": 23992,
        "averagePagesPerSessions": 9.96,
        "bouncerate": 23.62,
        "lastMonthData": {
          "totalSessions": 31746,
          "totalUsers": 21780,
          "pageviews": 406901
        },
        "aquisition": {
          "organic": 6179,
          "direct": 1456,
          "social": 2350,
          "referral": 355
        }
      }
    },
    {
      "name": "Thermae",
      "category": "Category 6",
      "server": "dedicated",
      "eCommerceData": {
        "conversions": 410,
        "averageSell": 200.29,
        "totalRevenue": 29714.18,
        "conversionRate": 2.5,
        "lastMonthData": {
          "conversions": 800,
          "averageSell": 200,
          "totalRevenue": 30000,
          "conversionRate": 4
        }
      },
      "analyticsData": {
        "totalSessions": 26960,
        "totalUsers": 25140,
        "pageviews": 23992,
        "averagePagesPerSessions": 9.96,
        "bouncerate": 23.62,
        "lastMonthData": {
          "totalSessions": 31746,
          "totalUsers": 21780,
          "pageviews": 406901
        },
        "aquisition": {
          "organic": 6179,
          "direct": 1456,
          "social": 2350,
          "referral": 355
        }
      }
    },
    {
      "name": "Arcade fashion",
      "category": "Medisch",
      "server": "dedicated",
      "eCommerceData": {
        "conversions": 410,
        "averageSell": 200.29,
        "totalRevenue": 29714.18,
        "conversionRate": 2.5,
        "lastMonthData": {
          "conversions": 800,
          "averageSell": 200,
          "totalRevenue": 30000,
          "conversionRate": 4
        }
      },
      "analyticsData": {
        "totalSessions": 26960,
        "totalUsers": 25140,
        "pageviews": 23992,
        "averagePagesPerSessions": 9.96,
        "bouncerate": 23.62,
        "lastMonthData": {
          "totalSessions": 31746,
          "totalUsers": 21780,
          "pageviews": 406901
        },
        "aquisition": {
          "organic": 6179,
          "direct": 1456,
          "social": 2350,
          "referral": 355
        }
      }
    },
    {
      "name": "Artex Fashion",
      "category": "Medisch",
      "server": "dedicated",
      "eCommerceData": {
        "conversions": 410,
        "averageSell": 200.29,
        "totalRevenue": 29714.18,
        "conversionRate": 2.5,
        "lastMonthData": {
          "conversions": 800,
          "averageSell": 200,
          "totalRevenue": 30000,
          "conversionRate": 4
        }
      },
      "analyticsData": {
        "totalSessions": 26960,
        "totalUsers": 25140,
        "pageviews": 23992,
        "averagePagesPerSessions": 9.96,
        "bouncerate": 23.62,
        "lastMonthData": {
          "totalSessions": 31746,
          "totalUsers": 21780,
          "pageviews": 406901
        },
        "aquisition": {
          "organic": 6179,
          "direct": 1456,
          "social": 2350,
          "referral": 355
        }
      }
    },
    {
      "name": "Carmelitana",
      "category": "Medisch",
      "server": "dedicated",
      "eCommerceData": {
        "conversions": 410,
        "averageSell": 200.29,
        "totalRevenue": 29714.18,
        "conversionRate": 2.5,
        "lastMonthData": {
          "conversions": 800,
          "averageSell": 200,
          "totalRevenue": 30000,
          "conversionRate": 4
        }
      },
      "analyticsData": {
        "totalSessions": 26960,
        "totalUsers": 25140,
        "pageviews": 23992,
        "averagePagesPerSessions": 9.96,
        "bouncerate": 23.62,
        "lastMonthData": {
          "totalSessions": 31746,
          "totalUsers": 21780,
          "pageviews": 406901
        },
        "aquisition": {
          "organic": 6179,
          "direct": 1456,
          "social": 2350,
          "referral": 355
        }
      }
    },
    {
      "name": "Huurland",
      "category": "Medisch",
      "server": "dedicated",
      "eCommerceData": {
        "conversions": 410,
        "averageSell": 200.29,
        "totalRevenue": 29714.18,
        "conversionRate": 2.5,
        "lastMonthData": {
          "conversions": 800,
          "averageSell": 200,
          "totalRevenue": 30000,
          "conversionRate": 4
        }
      },
      "analyticsData": {
        "totalSessions": 26960,
        "totalUsers": 25140,
        "pageviews": 23992,
        "averagePagesPerSessions": 9.96,
        "bouncerate": 23.62,
        "lastMonthData": {
          "totalSessions": 31746,
          "totalUsers": 21780,
          "pageviews": 406901
        },
        "aquisition": {
          "organic": 6179,
          "direct": 1456,
          "social": 2350,
          "referral": 355
        }
      }
    },
    {
      "name": "La Garde-robe",
      "category": "Medisch",
      "server": "dedicated",
      "eCommerceData": {
        "conversions": 410,
        "averageSell": 200.29,
        "totalRevenue": 29714.18,
        "conversionRate": 2.5,
        "lastMonthData": {
          "conversions": 800,
          "averageSell": 200,
          "totalRevenue": 30000,
          "conversionRate": 4
        }
      },
      "analyticsData": {
        "totalSessions": 26960,
        "totalUsers": 25140,
        "pageviews": 23992,
        "averagePagesPerSessions": 9.96,
        "bouncerate": 23.62,
        "lastMonthData": {
          "totalSessions": 31746,
          "totalUsers": 21780,
          "pageviews": 406901
        },
        "aquisition": {
          "organic": 6179,
          "direct": 1456,
          "social": 2350,
          "referral": 355
        }
      }
    },
    {
      "name": "Schoenen Verduyn",
      "category": "Medisch",
      "server": "dedicated",
      "eCommerceData": {
        "conversions": 410,
        "averageSell": 200.29,
        "totalRevenue": 29714.18,
        "conversionRate": 2.5,
        "lastMonthData": {
          "conversions": 800,
          "averageSell": 200,
          "totalRevenue": 30000,
          "conversionRate": 4
        }
      },
      "analyticsData": {
        "totalSessions": 26960,
        "totalUsers": 25140,
        "pageviews": 23992,
        "averagePagesPerSessions": 9.96,
        "bouncerate": 23.62,
        "lastMonthData": {
          "totalSessions": 31746,
          "totalUsers": 21780,
          "pageviews": 406901
        },
        "aquisition": {
          "organic": 6179,
          "direct": 1456,
          "social": 2350,
          "referral": 355
        }
      }
    },
    {
      "name": "Ralet",
      "category": "Medisch",
      "server": "dedicated",
      "eCommerceData": {
        "conversions": 410,
        "averageSell": 200.29,
        "totalRevenue": 29714.18,
        "conversionRate": 2.5,
        "lastMonthData": {
          "conversions": 800,
          "averageSell": 200,
          "totalRevenue": 30000,
          "conversionRate": 4
        }
      },
      "analyticsData": {
        "totalSessions": 26960,
        "totalUsers": 25140,
        "pageviews": 23992,
        "averagePagesPerSessions": 9.96,
        "bouncerate": 23.62,
        "lastMonthData": {
          "totalSessions": 31746,
          "totalUsers": 21780,
          "pageviews": 406901
        },
        "aquisition": {
          "organic": 6179,
          "direct": 1456,
          "social": 2350,
          "referral": 355
        }
      }
    },
    {
      "name": "Clem Vercammen",
      "category": "Medisch",
      "server": "dedicated",
      "eCommerceData": {
        "conversions": 410,
        "averageSell": 200.29,
        "totalRevenue": 29714.18,
        "conversionRate": 2.5,
        "lastMonthData": {
          "conversions": 800,
          "averageSell": 200,
          "totalRevenue": 30000,
          "conversionRate": 4
        }
      },
      "analyticsData": {
        "totalSessions": 26960,
        "totalUsers": 25140,
        "pageviews": 23992,
        "averagePagesPerSessions": 9.96,
        "bouncerate": 23.62,
        "lastMonthData": {
          "totalSessions": 31746,
          "totalUsers": 21780,
          "pageviews": 406901
        },
        "aquisition": {
          "organic": 6179,
          "direct": 1456,
          "social": 2350,
          "referral": 355
        }
      }
    },
    {
      "name": "Intro Fashion Store",
      "category": "Medisch",
      "server": "dedicated",
      "eCommerceData": {
        "conversions": 410,
        "averageSell": 200.29,
        "totalRevenue": 29714.18,
        "conversionRate": 2.5,
        "lastMonthData": {
          "conversions": 800,
          "averageSell": 200,
          "totalRevenue": 30000,
          "conversionRate": 4
        }
      },
      "analyticsData": {
        "totalSessions": 26960,
        "totalUsers": 25140,
        "pageviews": 23992,
        "averagePagesPerSessions": 9.96,
        "bouncerate": 23.62,
        "lastMonthData": {
          "totalSessions": 31746,
          "totalUsers": 21780,
          "pageviews": 406901
        },
        "aquisition": {
          "organic": 6179,
          "direct": 1456,
          "social": 2350,
          "referral": 355
        }
      }
    },
    {
      "name": "De Speelvogel",
      "category": "Medisch",
      "server": "dedicated",
      "eCommerceData": {
        "conversions": 410,
        "averageSell": 200.29,
        "totalRevenue": 29714.18,
        "conversionRate": 2.5,
        "lastMonthData": {
          "conversions": 800,
          "averageSell": 200,
          "totalRevenue": 30000,
          "conversionRate": 4
        }
      },
      "analyticsData": {
        "totalSessions": 26960,
        "totalUsers": 25140,
        "pageviews": 23992,
        "averagePagesPerSessions": 9.96,
        "bouncerate": 23.62,
        "lastMonthData": {
          "totalSessions": 31746,
          "totalUsers": 21780,
          "pageviews": 406901
        },
        "aquisition": {
          "organic": 6179,
          "direct": 1456,
          "social": 2350,
          "referral": 355
        }
      }
    },
    {
      "name": "Chaussures Jean Delaere",
      "category": "Medisch",
      "server": "dedicated",
      "eCommerceData": {
        "conversions": 410,
        "averageSell": 200.29,
        "totalRevenue": 29714.18,
        "conversionRate": 2.5,
        "lastMonthData": {
          "conversions": 800,
          "averageSell": 200,
          "totalRevenue": 30000,
          "conversionRate": 4
        }
      },
      "analyticsData": {
        "totalSessions": 26960,
        "totalUsers": 25140,
        "pageviews": 23992,
        "averagePagesPerSessions": 9.96,
        "bouncerate": 23.62,
        "lastMonthData": {
          "totalSessions": 31746,
          "totalUsers": 21780,
          "pageviews": 406901
        },
        "aquisition": {
          "organic": 6179,
          "direct": 1456,
          "social": 2350,
          "referral": 355
        }
      }
    },
    {
      "name": "Carmi Zemst Gabor Shop",
      "category": "Medisch",
      "server": "dedicated",
      "eCommerceData": {
        "conversions": 410,
        "averageSell": 200.29,
        "totalRevenue": 29714.18,
        "conversionRate": 2.5,
        "lastMonthData": {
          "conversions": 800,
          "averageSell": 200,
          "totalRevenue": 30000,
          "conversionRate": 4
        }
      },
      "analyticsData": {
        "totalSessions": 26960,
        "totalUsers": 25140,
        "pageviews": 23992,
        "averagePagesPerSessions": 9.96,
        "bouncerate": 23.62,
        "lastMonthData": {
          "totalSessions": 31746,
          "totalUsers": 21780,
          "pageviews": 406901
        },
        "aquisition": {
          "organic": 6179,
          "direct": 1456,
          "social": 2350,
          "referral": 355
        }
      }
    },
    {
      "name": "Carmi Zemst outlet",
      "category": "Medisch",
      "server": "dedicated",
      "eCommerceData": {
        "conversions": 410,
        "averageSell": 200.29,
        "totalRevenue": 29714.18,
        "conversionRate": 2.5,
        "lastMonthData": {
          "conversions": 800,
          "averageSell": 200,
          "totalRevenue": 30000,
          "conversionRate": 4
        }
      },
      "analyticsData": {
        "totalSessions": 26960,
        "totalUsers": 25140,
        "pageviews": 23992,
        "averagePagesPerSessions": 9.96,
        "bouncerate": 23.62,
        "lastMonthData": {
          "totalSessions": 31746,
          "totalUsers": 21780,
          "pageviews": 406901
        },
        "aquisition": {
          "organic": 6179,
          "direct": 1456,
          "social": 2350,
          "referral": 355
        }
      }
    },
    {
      "name": "Paris Londres",
      "category": "Medisch",
      "server": "dedicated",
      "eCommerceData": {
        "conversions": 410,
        "averageSell": 200.29,
        "totalRevenue": 29714.18,
        "conversionRate": 2.5,
        "lastMonthData": {
          "conversions": 800,
          "averageSell": 200,
          "totalRevenue": 30000,
          "conversionRate": 4
        }
      },
      "analyticsData": {
        "totalSessions": 26960,
        "totalUsers": 25140,
        "pageviews": 23992,
        "averagePagesPerSessions": 9.96,
        "bouncerate": 23.62,
        "lastMonthData": {
          "totalSessions": 31746,
          "totalUsers": 21780,
          "pageviews": 406901
        },
        "aquisition": {
          "organic": 6179,
          "direct": 1456,
          "social": 2350,
          "referral": 355
        }
      }
    },
    {
      "name": "Natuurkijkers",
      "category": "Medisch",
      "server": "dedicated",
      "eCommerceData": {
        "conversions": 410,
        "averageSell": 200.29,
        "totalRevenue": 29714.18,
        "conversionRate": 2.5,
        "lastMonthData": {
          "conversions": 800,
          "averageSell": 200,
          "totalRevenue": 30000,
          "conversionRate": 4
        }
      },
      "analyticsData": {
        "totalSessions": 26960,
        "totalUsers": 25140,
        "pageviews": 23992,
        "averagePagesPerSessions": 9.96,
        "bouncerate": 23.62,
        "lastMonthData": {
          "totalSessions": 31746,
          "totalUsers": 21780,
          "pageviews": 406901
        },
        "aquisition": {
          "organic": 6179,
          "direct": 1456,
          "social": 2350,
          "referral": 355
        }
      }
    },
    {
      "name": "Webshop 1",
      "category": "Medisch",
      "server": "dedicated",
      "eCommerceData": {
        "conversions": 410,
        "averageSell": 200.29,
        "totalRevenue": 29714.18,
        "conversionRate": 2.5,
        "lastMonthData": {
          "conversions": 800,
          "averageSell": 200,
          "totalRevenue": 30000,
          "conversionRate": 4
        }
      },
      "analyticsData": {
        "totalSessions": 26960,
        "totalUsers": 25140,
        "pageviews": 23992,
        "averagePagesPerSessions": 9.96,
        "bouncerate": 23.62,
        "lastMonthData": {
          "totalSessions": 31746,
          "totalUsers": 21780,
          "pageviews": 406901
        },
        "aquisition": {
          "organic": 6179,
          "direct": 1456,
          "social": 2350,
          "referral": 355
        }
      }
    },
    {
      "name": "Webshop 2",
      "category": "Medisch",
      "server": "dedicated",
      "eCommerceData": {
        "conversions": 410,
        "averageSell": 200.29,
        "totalRevenue": 29714.18,
        "conversionRate": 2.5,
        "lastMonthData": {
          "conversions": 800,
          "averageSell": 200,
          "totalRevenue": 30000,
          "conversionRate": 4
        }
      },
      "analyticsData": {
        "totalSessions": 26960,
        "totalUsers": 25140,
        "pageviews": 23992,
        "averagePagesPerSessions": 9.96,
        "bouncerate": 23.62,
        "lastMonthData": {
          "totalSessions": 31746,
          "totalUsers": 21780,
          "pageviews": 406901
        },
        "aquisition": {
          "organic": 6179,
          "direct": 1456,
          "social": 2350,
          "referral": 355
        }
      }
    },
    {
      "name": "Webshop 3",
      "category": "Medisch",
      "server": "dedicated",
      "eCommerceData": {
        "conversions": 410,
        "averageSell": 200.29,
        "totalRevenue": 29714.18,
        "conversionRate": 2.5,
        "lastMonthData": {
          "conversions": 800,
          "averageSell": 200,
          "totalRevenue": 30000,
          "conversionRate": 4
        }
      },
      "analyticsData": {
        "totalSessions": 26960,
        "totalUsers": 25140,
        "pageviews": 23992,
        "averagePagesPerSessions": 9.96,
        "bouncerate": 23.62,
        "lastMonthData": {
          "totalSessions": 31746,
          "totalUsers": 21780,
          "pageviews": 406901
        },
        "aquisition": {
          "organic": 6179,
          "direct": 1456,
          "social": 2350,
          "referral": 355
        }
      }
    },
    {
      "name": "Webshop 4",
      "category": "Medisch",
      "server": "dedicated",
      "eCommerceData": {
        "conversions": 410,
        "averageSell": 200.29,
        "totalRevenue": 29714.18,
        "conversionRate": 2.5,
        "lastMonthData": {
          "conversions": 800,
          "averageSell": 200,
          "totalRevenue": 30000,
          "conversionRate": 4
        }
      },
      "analyticsData": {
        "totalSessions": 26960,
        "totalUsers": 25140,
        "pageviews": 23992,
        "averagePagesPerSessions": 9.96,
        "bouncerate": 23.62,
        "lastMonthData": {
          "totalSessions": 31746,
          "totalUsers": 21780,
          "pageviews": 406901
        },
        "aquisition": {
          "organic": 6179,
          "direct": 1456,
          "social": 2350,
          "referral": 355
        }
      }
    },
    {
      "name": "Webshop 5",
      "category": "Medisch",
      "server": "dedicated",
      "eCommerceData": {
        "conversions": 410,
        "averageSell": 200.29,
        "totalRevenue": 29714.18,
        "conversionRate": 2.5,
        "lastMonthData": {
          "conversions": 800,
          "averageSell": 200,
          "totalRevenue": 30000,
          "conversionRate": 4
        }
      },
      "analyticsData": {
        "totalSessions": 26960,
        "totalUsers": 25140,
        "pageviews": 23992,
        "averagePagesPerSessions": 9.96,
        "bouncerate": 23.62,
        "lastMonthData": {
          "totalSessions": 31746,
          "totalUsers": 21780,
          "pageviews": 406901
        },
        "aquisition": {
          "organic": 6179,
          "direct": 1456,
          "social": 2350,
          "referral": 355
        }
      }
    }
  ]
}
